pyfilterlab/__init__.py
pyfilterlab/filters.py
pyfilterlab/plot.py
pyfilterlab-0.1.1.dist-info/licenses/LICENSE
pyfilterlab-0.1.1.dist-info/METADATA
pyfilterlab-0.1.1.dist-info/WHEEL
pyfilterlab-0.1.1.dist-info/top_level.txt
pyfilterlab-0.1.1.dist-info/RECORD
