Metadata-Version: 2.4
Name: pyfilterlab
Version: 0.1.1
Summary: Digital filter design and visualization toolkit
Author: Shinjan Saha
Author-email: shinjansaha02@gmail.com
Classifier: Programming Language :: Python :: 3
Classifier: Topic :: Scientific/Engineering
Requires-Python: >=3.7
License-File: LICENSE
Requires-Dist: numpy
Requires-Dist: scipy
Requires-Dist: matplotlib
Dynamic: author
Dynamic: author-email
Dynamic: classifier
Dynamic: description
Dynamic: description-content-type
Dynamic: license-file
Dynamic: requires-dist
Dynamic: requires-python
Dynamic: summary
